{
  "title": "Reactive Data Visualization",
  "slides": [
    { "title": "Welcome", "name": "firstSlide" },
    { "title": "Data Visualization", "name": "dataVisualization" },
      { "title": "Bertin's Theory", "name": "bertin", "indent": true },
      { "title": "Mackinlay's Theory", "name": "mackinlay", "indent": true },
    { "title": "Web Graphics", "name": "webGraphics" },
    { "title": "Using D3", "name": "usingd3", "image": "usingd3.png",
      "link": "https://github.com/mbostock/d3/wiki/Gallery" },
    { "title": "The Reality", "name": "reality", "image": "dots_reality.png" },
    { "title": "The Ideal", "name": "ideal", "image": "dots_ideal.png" },
    { "title": "Reusable D3", "name": "reusableD3" },
    { "title": "Rapid7 Dashboard", "name": "r7", "image": "mapDocs7.png",
      "link": "http://curran.github.io/portfolio/2013/UserInsightIngressDashboard.pdf" },
    { "title": "Model.js", "name": "model" },
    { "title": "Example Code", "name": "examples", "image": "barChart.png",
        "link": "../examples/viewer/#/1" },
    { "title": "Linked Views", "name": "linkedViews" },
    { "title": "Future Work", "name": "future" },
      { "title": "Bar Chart Flow", "name": "barChartFlow", "image": "barChartFlow.png", "indent": true },
      { "title": "Reactivis", "name": "reactivis", "image": "reactivis.png",
        "link": "http://curran.github.io/reactivis/docs/reactivis.html", "indent": true },
      { "title": "Dashboard Scaffold", "name": "dashboardscaffold", "image": "dashboardScaffold.png",
        "link": "http://curran.github.io/dashboardScaffoldExample/v0.1.0/index.html", "indent": true },
    { "title": "The End", "name": "lastSlide" }
  ]
}
